src/__init__.py
src/data_analysis_helper/__init__.py
src/data_analysis_helper/helper.py
tests/__init__.py
tests/integration/__init__.py
tests/integration/int_test.py
tests/unit/__init__.py
tests/unit/unit_test.py
eda_helper_tool-0.0.2.dist-info/LICENSE
eda_helper_tool-0.0.2.dist-info/METADATA
eda_helper_tool-0.0.2.dist-info/WHEEL
eda_helper_tool-0.0.2.dist-info/top_level.txt
eda_helper_tool-0.0.2.dist-info/RECORD
